<?xml version="1.0" encoding="UTF-8"?>
<!DOCTYPE suite SYSTEM "https://testng.org/testng-1.0.dtd">
<suite name="Suite">
<groups>
<run>
<include name="Liquid cooled"></include>
<include name="Air cooled"></include>
</run>
</groups>
  <test thread-count="5" name="Test">
    <classes>
      <class name="testNG2.Batch_exe_Bajaj"/>
      <class name="testNG2.Batch_exe_KTM"/>
      <class name="testNG2.Batch_exe_yamaha"/>
      <class name="testNG2.Batch_exe_RE"/>
      <class name="testNG2.Batch_exe_Honda"/>
      <class name="testNG2.Batch_exe_Yezdi"/>
    </classes>
  </test> <!-- Test -->
</suite> <!-- Suite -->
